{
  "$anchor": "vanilla-component",
  "$schema": "https://json-schema.org/draft/2020-12/schema",
  "type": "object",
  "$patch": {
    "source": {
      "$ref": "component"
    },
    "with": {
      "properties": {
        "_vanillaVis": {
          "type": "object",
          "title": "Vanilla",
          "default": {},
          "properties": {
            "_textAlignment": {
              "type": "object",
              "title": "Text alignment",
              "default": {},
              "properties": {
                "_title": {
                  "type": "string",
                  "title": "Title alignment",
                  "description": "Set the alignment of the component title. Left: Aligns the title to the left of the container. Center: Aligns the title to the center of the container. Right: Aligns the title to the right of the container. The alignment automatically inverses for right-to-left languages. The default is `` which inherits the natural page direction.",
                  "default": "",
                  "enum": [
                    "",
                    "left",
                    "center",
                    "right"
                  ],
                  "_backboneForms": "Select"
                },
                "_body": {
                  "type": "string",
                  "title": "Body alignment",
                  "description": "Set the alignment of the component body. Left: Aligns the body to the left of the container. Center: Aligns the body to the center of the container. Right: Aligns the body to the right of the container. The alignment automatically inverses for right-to-left languages. The default is `` which inherits the natural page direction.",
                  "default": "",
                  "enum": [
                    "",
                    "left",
                    "center",
                    "right"
                  ],
                  "_backboneForms": "Select"
                },
                "_instruction": {
                  "type": "string",
                  "title": "Instruction alignment",
                  "description": "Set the alignment of the component instruction. Left: Aligns the instruction to the left of the container. Center: Aligns the instruction to the center of the container. Right: Aligns the instruction to the right of the container. The alignment automatically inverses for right-to-left languages. The default is `` which inherits the natural page direction.",
                  "default": "",
                  "enum": [
                    "",
                    "left",
                    "center",
                    "right"
                  ],
                  "_backboneForms": "Select"
                }
              }
            }
          }
        }
      }
    }
  }
}
